generate/__init__.py
generate/access_token_manager.py
generate/chat_completion/__init__.py
generate/chat_completion/base.py
generate/chat_completion/cost_caculator.py
generate/chat_completion/message/__init__.py
generate/chat_completion/message/core.py
generate/chat_completion/message/exception.py
generate/chat_completion/message/utils.py
generate/chat_completion/model_output.py
generate/chat_completion/models/__init__.py
generate/chat_completion/models/anthropic.py
generate/chat_completion/models/azure.py
generate/chat_completion/models/baichuan.py
generate/chat_completion/models/bailian.py
generate/chat_completion/models/dashscope.py
generate/chat_completion/models/dashscope_multimodal.py
generate/chat_completion/models/deepseek.py
generate/chat_completion/models/hunyuan.py
generate/chat_completion/models/minimax.py
generate/chat_completion/models/minimax_legacy.py
generate/chat_completion/models/minimax_pro.py
generate/chat_completion/models/moonshot.py
generate/chat_completion/models/openai.py
generate/chat_completion/models/openai_like.py
generate/chat_completion/models/stepfun.py
generate/chat_completion/models/test.py
generate/chat_completion/models/wenxin.py
generate/chat_completion/models/yi.py
generate/chat_completion/models/zhipu.py
generate/chat_completion/printer.py
generate/chat_completion/stream_manager.py
generate/chat_completion/tool.py
generate/highlevel.py
generate/http.py
generate/image_generation/__init__.py
generate/image_generation/base.py
generate/image_generation/models/__init__.py
generate/image_generation/models/baidu.py
generate/image_generation/models/openai.py
generate/image_generation/models/qianfan.py
generate/image_generation/models/zhipu.py
generate/model.py
generate/modifiers/__init__.py
generate/modifiers/agent.py
generate/modifiers/hook.py
generate/modifiers/limit.py
generate/modifiers/session.py
generate/modifiers/structure.py
generate/platforms/__init__.py
generate/platforms/anthropic.py
generate/platforms/azure.py
generate_core-0.4.3.dist-info/LICENSE
generate_core-0.4.3.dist-info/METADATA
generate_core-0.4.3.dist-info/WHEEL
generate_core-0.4.3.dist-info/RECORD
